WeiYewuliangShenDazaoAliWenyuYonghuJiNeirongYunyingPingtaiJishuShijian/README.md
WeiYewuliangShenDazaoAliWenyuYonghuJiNeirongYunyingPingtaiJishuShijian/__init__.py
WeiYewuliangShenDazaoAliWenyuYonghuJiNeirongYunyingPingtaiJishuShijian/__main__.py
WeiYewuliangShenDazaoAliWenyuYonghuJiNeirongYunyingPingtaiJishuShijian/file.pdf
WeiYewuliangShenDazaoAliWenyuYonghuJiNeirongYunyingPingtaiJishuShijian/index.html
wei_yewuliang_shen_dazao_ali_wenyu_yonghu_ji_neirong_yunying_pingtai_jishu_shijian-2024.3.6.0.dist-info/METADATA
wei_yewuliang_shen_dazao_ali_wenyu_yonghu_ji_neirong_yunying_pingtai_jishu_shijian-2024.3.6.0.dist-info/WHEEL
wei_yewuliang_shen_dazao_ali_wenyu_yonghu_ji_neirong_yunying_pingtai_jishu_shijian-2024.3.6.0.dist-info/entry_points.txt
wei_yewuliang_shen_dazao_ali_wenyu_yonghu_ji_neirong_yunying_pingtai_jishu_shijian-2024.3.6.0.dist-info/top_level.txt
wei_yewuliang_shen_dazao_ali_wenyu_yonghu_ji_neirong_yunying_pingtai_jishu_shijian-2024.3.6.0.dist-info/RECORD
