Metadata-Version: 2.1
Name: wei-yewuliang-shen-dazao-ali-wenyu-yonghu-ji-neirong-yunying-pingtai-jishu-shijian
Version: 2024.3.6.0
Summary: 为业务量身打造——阿里文娱用户及内容运营平台技术实践
Home-page: https://github.com/apachecn/wei-yewuliang-shen-dazao-ali-wenyu-yonghu-ji-neirong-yunying-pingtai-jishu-shijian
Author: ApacheCN
Author-email: apachecn@163.com
Classifier: Development Status :: 4 - Beta
Classifier: Environment :: Console
Classifier: Intended Audience :: Developers
Classifier: Intended Audience :: End Users/Desktop
Classifier: License :: Other/Proprietary License
Classifier: Natural Language :: Chinese (Simplified)
Classifier: Natural Language :: English
Classifier: Operating System :: OS Independent
Classifier: Programming Language :: Python :: 3
Classifier: Programming Language :: Python :: 3 :: Only
Classifier: Programming Language :: Python :: 3.6
Classifier: Programming Language :: Python :: 3.7
Classifier: Topic :: Text Processing :: Markup :: Markdown
Classifier: Topic :: Text Processing :: Markup :: HTML
Classifier: Topic :: Internet :: WWW/HTTP
Classifier: Topic :: Software Development :: Documentation
Classifier: Topic :: Documentation
Requires-Python: >=3.6
